flax_id/__init__.py
flax_id/flax_id.py
flax_id/tests.py
flax_id/django/__init__.py
flax_id/django/fields.py
flax_id/django/models.py
python_flax_id-1.1.0.dist-info/DESCRIPTION.rst
python_flax_id-1.1.0.dist-info/METADATA
python_flax_id-1.1.0.dist-info/RECORD
python_flax_id-1.1.0.dist-info/WHEEL
python_flax_id-1.1.0.dist-info/metadata.json
python_flax_id-1.1.0.dist-info/top_level.txt
