Metadata-Version: 2.0
Name: python-flax-id
Version: 1.1.0
Summary: Python implementation of Flax ID algorithm
Home-page: https://github.com/ezhome/python-flax-id
Author: Ezhome Engineers
Author-email: engineers@ezhome.com
License: Other/Proprietary License
Keywords: ezhome flax flax-id
Platform: any
Classifier: Development Status :: 5 - Production/Stable
Classifier: Environment :: Web Environment
Classifier: Intended Audience :: Developers
Classifier: License :: Other/Proprietary License
Classifier: Operating System :: OS Independent
Classifier: Programming Language :: Python :: 2
Classifier: Programming Language :: Python :: 2.7
Classifier: Programming Language :: Python :: 3
Classifier: Programming Language :: Python :: 3.5
Classifier: Topic :: Internet :: WWW/HTTP :: Dynamic Content
Classifier: Topic :: Software Development :: Libraries :: Python Modules
Classifier: Topic :: Utilities
